pynvest/__init__.py
pynvest/scrappers/__init__.py
pynvest/scrappers/fundamentus.py
pynvest/utils/__init__.py
pynvest/utils/log.py
tests/__init__.py
tests/conftest.py
tests/test_scrappers_fundamentus.py
tests/test_utils_log.py
pynvest-0.1.2.dist-info/LICENSE
pynvest-0.1.2.dist-info/METADATA
pynvest-0.1.2.dist-info/WHEEL
pynvest-0.1.2.dist-info/top_level.txt
pynvest-0.1.2.dist-info/RECORD
