Metadata-Version: 2.1
Name: pynvest
Version: 0.1.2
Summary: Uma forma fácil de extrair indicadores de ativos da bolsa B3
Home-page: https://pynvest.readthedocs.io/pt/latest/
Author: Thiago Panini
Author-email: panini.development@gmail.com
License: MIT
Keywords: B3,Ativos,Fundos Imobiliários,Mercado Financeiro
Classifier: Programming Language :: Python :: 3
Classifier: Development Status :: 4 - Beta
Classifier: Intended Audience :: Developers
Classifier: Natural Language :: Portuguese (Brazilian)
Classifier: License :: OSI Approved :: MIT License
Classifier: Operating System :: OS Independent
Classifier: Programming Language :: Python :: 3.8
Classifier: Programming Language :: Python :: 3.9
Classifier: Programming Language :: Python :: 3.10
Classifier: Topic :: Software Development :: Libraries :: Python Modules
Requires-Python: >=3.0.0
License-File: LICENSE
Requires-Dist: requests
Requires-Dist: beautifulsoup4
Requires-Dist: lxml
Requires-Dist: pandas
